pyBJD/__init__.py
pyBJD/pyBJD.py
pyBJD-1.0.dist-info/DESCRIPTION.rst
pyBJD-1.0.dist-info/METADATA
pyBJD-1.0.dist-info/RECORD
pyBJD-1.0.dist-info/WHEEL
pyBJD-1.0.dist-info/metadata.json
pyBJD-1.0.dist-info/top_level.txt
