Metadata-Version: 2.0
Name: pyBJD
Version: 1.0
Summary: A Very Basic JD to BJD conversion API
Home-page: https://github.com/tboudreaux/pyBJD
Author: Thomas Boudreaux
Author-email: thomas@boudreauxmail.com
License: MIT
Platform: UNKNOWN
Classifier: Development Status :: 5 - Production/Stable
Classifier: Intended Audience :: Science/Research
Classifier: License :: OSI Approved :: MIT License
Classifier: Programming Language :: Python :: 3
Requires-Dist: astropy (>=1.3.2)
Requires-Dist: numpy (>=1.12.0)
Requires-Dist: selenium (>=3.4.2)
